fish_prode/__init__.py
fish_prode/css/bootstrap-grid.css
fish_prode/css/bootstrap-grid.css.map
fish_prode/css/bootstrap-grid.min.css
fish_prode/css/bootstrap-grid.min.css.map
fish_prode/css/bootstrap-reboot.css
fish_prode/css/bootstrap-reboot.css.map
fish_prode/css/bootstrap-reboot.min.css
fish_prode/css/bootstrap-reboot.min.css.map
fish_prode/css/bootstrap.css
fish_prode/css/bootstrap.css.map
fish_prode/css/bootstrap.min.css
fish_prode/css/bootstrap.min.css.map
fish_prode/css/font-awesome.css
fish_prode/css/font-awesome.min.css
fish_prode/css/fonts.css
fish_prode/css/home.css
fish_prode/css/style.css
fish_prode/css/tether-theme-arrows-dark.css
fish_prode/css/tether-theme-arrows-dark.min.css
fish_prode/css/tether-theme-arrows.css
fish_prode/css/tether-theme-arrows.min.css
fish_prode/css/tether-theme-basic.css
fish_prode/css/tether-theme-basic.min.css
fish_prode/css/tether.css
fish_prode/css/tether.min.css
fish_prode/fonts/FontAwesome.otf
fish_prode/fonts/fontawesome-webfont.eot
fish_prode/fonts/fontawesome-webfont.svg
fish_prode/fonts/fontawesome-webfont.ttf
fish_prode/fonts/fontawesome-webfont.woff
fish_prode/fonts/fontawesome-webfont.woff2
fish_prode/fonts/lobster-regular-latin-ext.woff2
fish_prode/fonts/lobster-regular-latin.woff2
fish_prode/fonts/raleway-regular-latin-ext.woff2
fish_prode/fonts/raleway-regular-latin.woff2
fish_prode/js/bootstrap.js
fish_prode/js/bootstrap.js.old
fish_prode/js/bootstrap.min.js
fish_prode/js/bootstrap.min.js.old
fish_prode/js/jquery.min.js
fish_prode/js/npm.js
fish_prode/js/tether.js
fish_prode/js/tether.min.js
fish_prode/sections/__init__.py
fish_prode/sections/app.py
fish_prode/sections/routes.py
fish_prode/sections/probe_design/__init__.py
fish_prode/sections/probe_design/app.py
fish_prode/sections/probe_design/enquirer.py
fish_prode/sections/probe_design/query.py
fish_prode/sections/probe_design/queue.py
fish_prode/sections/probe_design/routes.py
fish_prode-1.1.0.post2.dist-info/METADATA
fish_prode-1.1.0.post2.dist-info/RECORD
fish_prode-1.1.0.post2.dist-info/WHEEL
fish_prode-1.1.0.post2.dist-info/top_level.txt
