Metadata-Version: 2.1
Name: fish-prode
Version: 1.1.0.post2
Summary: A FISH probe design web interface.
Home-page: https://github.com/ggirelli/fish-prode
Author: Gabriele Girelli
Author-email: gabriele.girelli@scilifelab.se
License: MIT
Keywords: biology cell DNA RNA FISH fluorescence hybridization bioimaging genome
Platform: UNKNOWN
Classifier: Development Status :: 4 - Beta
Classifier: Intended Audience :: Science/Research
Classifier: Topic :: Scientific/Engineering :: Bio-Informatics
Classifier: License :: OSI Approved :: MIT License
Classifier: Programming Language :: Python :: 3 :: Only
Requires-Dist: bottle (>=0.12.13)
Requires-Dist: matplotlib (>=2.2.2)
Requires-Dist: numpy (>=1.14.2)
Requires-Dist: pandas (>=0.22.0)
Requires-Dist: paste (>=2.0.3)
Requires-Dist: scipy (>=1.0.0)
